scr/isautil/CombineColors.py
scr/isautil/__init__.py
scr/isautil/zut.py
scr/isautil/.ipynb_checkpoints/__init__-checkpoint.py
scr/isautil/.ipynb_checkpoints/zut-checkpoint.py
isautil-0.0.2.dist-info/METADATA
isautil-0.0.2.dist-info/WHEEL
isautil-0.0.2.dist-info/licenses/LICENSE
isautil-0.0.2.dist-info/RECORD
