Metadata-Version: 2.1
Name: isautil
Version: 0.0.2
Summary: unilities
Author-email: isamutee <isamutee@gmail.com>
License-File: LICENSE
Classifier: License :: OSI Approved :: MIT License
Classifier: Operating System :: OS Independent
Classifier: Programming Language :: Python :: 3
Requires-Python: >=3
